cluster_pub/__init__.py
cluster_pub/__main__.py
cluster_pub/abstract_embedder/__init__.py
cluster_pub/abstract_embedder/abstract_embedder.py
cluster_pub/abstract_similarity_calculator/__init__.py
cluster_pub/abstract_similarity_calculator/abstract_similarity_calculator.py
cluster_pub/bibliography_abstract_processor/__init__.py
cluster_pub/bibliography_abstract_processor/bibliography_abstract_processor.py
cluster_pub/bibliography_abstract_processor/schemas.py
cluster_pub/bibliography_parsers/__init__.py
cluster_pub/bibliography_parsers/bibliography_file_extension_enum.py
cluster_pub/bibliography_parsers/bibliography_loader.py
cluster_pub/bibliography_parsers/bibliography_loader_factory.py
cluster_pub/bibliography_parsers/bibliography_parser.py
cluster_pub/bibliography_parsers/bibtex/__init__.py
cluster_pub/bibliography_parsers/bibtex/bibtex_entry_parser.py
cluster_pub/bibliography_parsers/bibtex/bibtex_loader.py
cluster_pub/bibliography_parsers/exceptions.py
cluster_pub/bibliography_parsers/file_enconding_enum.py
cluster_pub/bibliography_parsers/nbib/__init__.py
cluster_pub/bibliography_parsers/nbib/nbib_loader.py
cluster_pub/bibliography_parsers/ris/__init__.py
cluster_pub/bibliography_parsers/ris/ris_loader.py
cluster_pub/bibliography_parsers/schemas.py
cluster_pub/cluster_evaluation.py
cluster_pub/cluster_publications.py
cluster_pub/clustering_evaluator.py
cluster_pub/dendogram_builder/__init__.py
cluster_pub/dendogram_builder/dendogram_builder.py
cluster_pub/main.py
cluster_pub-0.2.2.dist-info/METADATA
cluster_pub-0.2.2.dist-info/WHEEL
cluster_pub-0.2.2.dist-info/entry_points.txt
cluster_pub-0.2.2.dist-info/RECORD
