Metadata-Version: 2.1
Name: cluster-pub
Version: 0.2.2
Summary: CLI to cluster scientific papers
Author: felipe barcelos
Author-email: felipebarcelos@ufu.br
Requires-Python: >=3.11,<3.12
Classifier: Programming Language :: Python :: 3
Classifier: Programming Language :: Python :: 3.11
Requires-Dist: bibtexparser (>=1.4.2,<1.5.0)
Requires-Dist: matplotlib (>=3.9.2,<3.10.0)
Requires-Dist: nbib (>=0.3.2,<0.4.0)
Requires-Dist: pillow (>=11.0.0,<11.1.0)
Requires-Dist: rispy (>=0.9.0,<0.10.0)
Requires-Dist: scikit-learn (>=1.5.2,<1.6.0)
Requires-Dist: scipy (>=1.14.1,<1.15.0)
Requires-Dist: typer (>=0.13.0,<0.14.0)
